py3status_reddit/__init__.py
py3status_reddit/__version__.py
py3status_reddit/reddit.py
py3status_reddit/webserver.py
py3status_reddit-1.0.1.dist-info/METADATA
py3status_reddit-1.0.1.dist-info/WHEEL
py3status_reddit-1.0.1.dist-info/entry_points.txt
py3status_reddit-1.0.1.dist-info/RECORD
