Metadata-Version: 2.1
Name: py3status-reddit
Version: 1.0.1
Summary: py3status module showing reddit unread messages
Author: Alessandro -oggei- Ogier
Author-email: alessandro.ogier@gmail.com
Requires-Python: >=3.6.2,<4.0.0
Classifier: Programming Language :: Python :: 3
Classifier: Programming Language :: Python :: 3.7
Classifier: Programming Language :: Python :: 3.8
Classifier: Programming Language :: Python :: 3.9
Classifier: Programming Language :: Python :: 3.10
Classifier: Programming Language :: Python :: 3.11
Requires-Dist: praw (>=7.2.0,<8.0.0)
Requires-Dist: xdg (>=5.0.2,<6.0.0)
